AliceCli/AliceCli.py
AliceCli/MainMenu.py
AliceCli/__init__.py
AliceCli/alice/__init__.py
AliceCli/alice/alice.py
AliceCli/install/__init__.py
AliceCli/install/install.py
AliceCli/tests/__init__.py
AliceCli/tests/test_alice.py
AliceCli/tests/test_aliceCli.py
AliceCli/tests/test_commons.py
AliceCli/tests/test_install.py
AliceCli/tests/test_mainMenu.py
AliceCli/tests/test_utils.py
AliceCli/utils/__init__.py
AliceCli/utils/commons.py
AliceCli/utils/decorators.py
AliceCli/utils/utils.py
projectalice_cli-1.3.30.dist-info/LICENSE
projectalice_cli-1.3.30.dist-info/METADATA
projectalice_cli-1.3.30.dist-info/WHEEL
projectalice_cli-1.3.30.dist-info/entry_points.txt
projectalice_cli-1.3.30.dist-info/top_level.txt
projectalice_cli-1.3.30.dist-info/RECORD
