Metadata-Version: 2.1
Name: projectalice-cli
Version: 1.3.30
Summary: Project Alice CLI tool
Home-page: https://github.com/project-alice-assistant/AliceCLI
Author: ProjectAlice
Author-email: laurentchervet@bluewin.ch
Maintainer: Psychokiller1888
License: GPL-3.0
Platform: UNKNOWN
Classifier: Development Status :: 5 - Production/Stable
Classifier: Environment :: Console
Classifier: Intended Audience :: End Users/Desktop
Classifier: License :: OSI Approved :: GNU General Public License v3 (GPLv3)
Classifier: Operating System :: OS Independent
Classifier: Programming Language :: Python :: 3.8
Classifier: Topic :: Home Automation
Classifier: Topic :: System :: Installation/Setup
Requires-Python: >=3.8
Requires-Dist: click (~=8.0.3)
Requires-Dist: paramiko (~=2.8.1)
Requires-Dist: InquirerPy (~=0.3.1)
Requires-Dist: networkscan (~=1.0.9)
Requires-Dist: pyyaml (~=6.0)
Requires-Dist: requests (~=2.26.0)
Requires-Dist: psutil (~=5.8.0)
Requires-Dist: beautifulsoup4 (~=4.10.0)
Requires-Dist: tqdm (~=4.62.3)
Requires-Dist: pytest (~=6.2.5)
Requires-Dist: coverage (~=6.2)
Requires-Dist: pytest-cov (~=3.0.0)
Requires-Dist: coveralls (~=3.3.1)
Requires-Dist: tomli (~=2.0.0)
Requires-Dist: six (~=1.16.0)
Requires-Dist: ProjectAlice
